netapp_lib/__init__.py
netapp_lib/changelog.rst
netapp_lib/exceptions.py
netapp_lib/api/__init__.py
netapp_lib/api/rest/__init__.py
netapp_lib/api/rest/rest.py
netapp_lib/api/zapi/__init__.py
netapp_lib/api/zapi/errors.py
netapp_lib/api/zapi/zapi.py
netapp_lib-2021.6.25.data/data/LICENSE.txt
netapp_lib-2021.6.25.dist-info/LICENSE.txt
netapp_lib-2021.6.25.dist-info/METADATA
netapp_lib-2021.6.25.dist-info/WHEEL
netapp_lib-2021.6.25.dist-info/top_level.txt
netapp_lib-2021.6.25.dist-info/RECORD
